{
	"@context": {
	    "@vocab": "http://www.semanticweb.org/ontologies/mythologie#",
	    "myth": "http://www.semanticweb.org/ontologies/mythologie/",
	    "auth": "http://www.semanticweb.org/ontologies/mythologie/author/",
	    "m": "http://www.w3.org/mythologie/class#",
	    "p": "http://www.w3.org/mythologie/property#",
	    "owl": "http://www.w3.org/2002/07/owl#",
	    "dc": "http://purl.org/dc/elements/1.1/",
	    "dcterms": "http://purl.org/dc/terms/",
		"skos": "http://www.w3.org/2004/02/skos/core#",
		"xsd": "http://www.w3.org/2001/XMLSchema#",
		"ical": "http://www.w3.org/2002/12/cal/ical#",
		"skos:broader": {
			"@type": "@id"
		},
		"skos:inScheme": {
			"@type": "@id"
		},
		"skos:related": {
			"@type": "@id"
		},
		"skos:altLabel": {"@container" : "@language" },
		"skos:prefLabel": {"@container" : "@language"},
		"skos:definition": {"@container" : "@language"},
		"title": { "@container" : "@language" },
		"p:thumbnail": {"@type": "xsd:string"},
		"p:regular": {"@type": "xsd:string"},
		"dcterms:modified":{"@type": "dcterms:W3CDTF"},
		"skos:narrower": {"@type": "@id"},
		"skos:hasTopConcept": {
			"@type": "@id"
		},
		"skos:topConceptOf": {
			"@type": "@id"
		},
		"p:hasGender":{ "@type": "@id" },
		"ical:dtstart": { "@type": "xsd:dateTime" }
		},
"@graph": [{"@id": "auth:Homer",
	"@type": ["skos:Concept","Poet"],
	"skos:inScheme": "myth:Litterature",
	"skos:prefLabel": 
	    {"en": "Homer",
	     "fr": "Homère"
		}
	},
	{"@id": "auth:Euripide",
	"@type": ["skos:Concept","Tragique"],
	"skos:inScheme": "myth:Litterature",
	"skos:prefLabel": 
	    {"en": "Euripide",
	     "fr": "Euripide"
		}
	},
	{"@id": "auth:Aristote",
	"@type": ["skos:Concept","Philosoph"],
	"skos:inScheme": "myth:Litterature",
	"skos:prefLabel": 
	    {"en": "Aristote",
	     "fr": "Aristote"
		}
	}
    ]
}